[
  {
    "postId": "774692",
    "title": "【已出】Lightlayer LA-VG01-A 12.49刀年付",
    "reply": "已出帮顶，价格不错，可惜来晚了啊"
  },
  {
    "postId": "774677",
    "title": "第一次坐牢十天,刚刚出狱",
    "reply": "你这标题，我还以为真进去了，注意身体啊"
  },
  {
    "postId": "774676",
    "title": "DMIT HKG T1 能拿来拉美国鸡了",
    "reply": "拉美西挺爽的，就是国内连过去是个问题"
  },
  {
    "postId": "774673",
    "title": "MeSIM 乐天降价 57.48 元",
    "reply": "限速256k确实太折磨了，也就出门防失联用"
  },
  {
    "postId": "774669",
    "title": "大家都用什么方式ssh远程？",
    "reply": "原始人+1，不过现在慢慢换密钥登录了"
  },
  {
    "postId": "774663",
    "title": "汇丰HK的地址能改成HK的么？",
    "reply": "劝你别乱改真实银行地址，容易被风控关户"
  },
  {
    "postId": "774650",
    "title": "万万没想到，netcup的鸡都能溢价好几百出手了",
    "reply": "炒鸡炒得太离谱了，以前确实都是直接送的"
  },
  {
    "postId": "774642",
    "title": "提交工单，有个优先级高中低，选哪个",
    "reply": "大厂会按优先级，小厂基本都是摆设，随便选"
  },
  {
    "postId": "774625",
    "title": "DMIT 终于补货了",
    "reply": "这没优化线路的机器也发aff，确实有点水"
  },
  {
    "postId": "774616",
    "title": "DMIT HK Pro NQ留",
    "reply": "DMIT的HK Pro确实稳，就是买不起啊哈"
  },
  {
    "postId": "774613",
    "title": "vps如果拿来做代理自用,什么是重要的",
    "reply": "绝对是线路优化最重要，线路不好带宽再大也没用"
  },
  {
    "postId": "774608",
    "title": "[抽奖]MediaStationGo-EMBY一站式开服+自建影视中心新方案-一年无限用户授权码3个",
    "reply": "支持开源项目！抽个分母，祝项目越来越好"
  },
  {
    "postId": "774607",
    "title": "【收鸡】总价1K 收品川239",
    "reply": "正价品川239这价格真能收到吗？帮顶了"
  },
  {
    "postId": "774603",
    "title": "请教三网持续ping那种图使用什么监控的",
    "reply": "一般是用komari或者哪吒探针，点开有延迟图"
  },
  {
    "postId": "774602",
    "title": "dmit HKG T1这鸡有啥用？",
    "reply": "就是个普通落地机或者建站机，别指望直连了"
  },
  {
    "postId": "774598",
    "title": "【停收】去收Gen2了",
    "reply": "Gen2确实香，不知道能不能收到，祝早收"
  },
  {
    "postId": "774597",
    "title": "🇺🇸0.6u的美国号码实测可以注册paypal，TG，美国实体号",
    "reply": "0.6u月租确实便宜，不过写卡麻烦不？"
  },
  {
    "postId": "774592",
    "title": "我买的gg卡只有单卡，没有外面的卡板，有影响吗",
    "reply": "空白卡一般激活码都在卡板上，没卡板不好激活"
  },
  {
    "postId": "774586",
    "title": "【NQ测评】DMIT HKG.AS3.T1.WEE",
    "reply": "AS3这机器也就落地用了，直连拉跨得不行"
  },
  {
    "postId": "774583",
    "title": "坏菜了，git commit生成了个不吉利的hash，我都要重新生成一次push",
    "reply": "你这强迫症也是没谁了，直接amend重新提交"
  }
]
